tigergraphx/__init__.py
tigergraphx/config/__init__.py
tigergraphx/config/base_config.py
tigergraphx/config/endpoint_definitions.yaml
tigergraphx/config/graph_db/__init__.py
tigergraphx/config/graph_db/loading_job_config.py
tigergraphx/config/graph_db/schema/__init__.py
tigergraphx/config/graph_db/schema/attribute_schema.py
tigergraphx/config/graph_db/schema/data_type.py
tigergraphx/config/graph_db/schema/edge_schema.py
tigergraphx/config/graph_db/schema/graph_schema.py
tigergraphx/config/graph_db/schema/node_schema.py
tigergraphx/config/graph_db/schema/reserved_keywords.py
tigergraphx/config/graph_db/schema/vector_attribute_schema.py
tigergraphx/config/graph_db/tigergraph_connection_config.py
tigergraphx/config/logging_config.yaml
tigergraphx/config/query/__init__.py
tigergraphx/config/query/edge_spec.py
tigergraphx/config/query/neighbor_spec.py
tigergraphx/config/query/node_spec.py
tigergraphx/config/settings/__init__.py
tigergraphx/config/settings/chat_settings.py
tigergraphx/config/settings/embedding_settings.py
tigergraphx/config/settings/llm_settings.py
tigergraphx/config/settings/settings.py
tigergraphx/config/settings/vector_db_settings.py
tigergraphx/core/__init__.py
tigergraphx/core/graph.py
tigergraphx/core/graph_context.py
tigergraphx/core/managers/__init__.py
tigergraphx/core/managers/base_manager.py
tigergraphx/core/managers/data_manager.py
tigergraphx/core/managers/edge_manager.py
tigergraphx/core/managers/node_manager.py
tigergraphx/core/managers/query_manager.py
tigergraphx/core/managers/schema_manager.py
tigergraphx/core/managers/statistics_manager.py
tigergraphx/core/managers/vector_manager.py
tigergraphx/core/tigergraph_api/__init__.py
tigergraphx/core/tigergraph_api/api/__init__.py
tigergraphx/core/tigergraph_api/api/admin_api.py
tigergraphx/core/tigergraph_api/api/base_api.py
tigergraphx/core/tigergraph_api/api/data_source_api.py
tigergraphx/core/tigergraph_api/api/edge_api.py
tigergraphx/core/tigergraph_api/api/gsql_api.py
tigergraphx-0.2.15.dist-info/LICENCE
tigergraphx-0.2.15.dist-info/METADATA
tigergraphx-0.2.15.dist-info/WHEEL
tigergraphx-0.2.15.dist-info/RECORD
